thinc.libs/libgcc_s-a3a07607.so.1
thinc.libs/libstdc++-496613c0.so.6.0.32
thinc/loss.py
thinc/mypy.py
thinc/model.py
thinc/api.py
thinc/__init__.py
thinc/py.typed
thinc/util.py
thinc/compat.py
thinc/about.py
thinc/types.py
thinc/config.py
thinc/schedules.py
thinc/initializers.py
thinc/optimizers.py
thinc/__init__.pxd
thinc/tests/test_util.py
thinc/tests/test_import__all__.py
thinc/tests/test_loss.py
thinc/tests/test_initializers.py
thinc/tests/enable_mxnet.py
thinc/tests/test_indexing.py
thinc/tests/test_optimizers.py
thinc/tests/test_serialize.py
thinc/tests/conftest.py
thinc/tests/test_examples.py
thinc/tests/__init__.py
thinc/tests/test_types.py
thinc/tests/util.py
thinc/tests/test_schedules.py
thinc/tests/test_config.py
thinc/tests/strategies.py
thinc/tests/enable_tensorflow.py
thinc/tests/model/test_model.py
thinc/tests/model/__init__.py
thinc/tests/model/test_validation.py
thinc/tests/regression/test_issue564.py
thinc/tests/regression/test_issue208.py
thinc/tests/regression/__init__.py
thinc/tests/regression/issue519/test_issue519.py
thinc/tests/regression/issue519/__init__.py
thinc/tests/regression/issue519/program.py
thinc/tests/backends/test_mem.py
thinc/tests/backends/test_mps_ops.py
thinc/tests/backends/test_ops.py
thinc/tests/backends/__init__.py
thinc/tests/backends/_apple_blas/__init__.py
thinc/tests/backends/_apple_blas/test_gemm.py
thinc/tests/shims/test_pytorch_grad_scaler.py
thinc/tests/shims/__init__.py
thinc/tests/mypy/test_mypy.py
thinc/tests/mypy/__init__.py
thinc/tests/mypy/modules/fail_no_plugin.py
thinc/tests/mypy/modules/fail_plugin.py
thinc/tests/mypy/modules/success_plugin.py
thinc/tests/mypy/modules/success_no_plugin.py
thinc/tests/mypy/modules/__init__.py
thinc/tests/mypy/configs/mypy-default.ini
thinc/tests/mypy/configs/mypy-plugin.ini
thinc/tests/mypy/outputs/fail-no-plugin.txt
thinc/tests/mypy/outputs/success-plugin.txt
thinc/tests/mypy/outputs/fail-plugin.txt
thinc-9.1.1.dist-info/LICENSE
thinc-9.1.1.dist-info/METADATA
thinc-9.1.1.dist-info/top_level.txt
thinc-9.1.1.dist-info/RECORD
thinc-9.1.1.dist-info/WHEEL
thinc-9.1.1.dist-info/entry_points.txt
