Metadata-Version: 2.1
Name: thinc
Version: 9.1.1
Summary: A refreshing functional take on deep learning, compatible with your favorite libraries
Home-page: https://github.com/explosion/thinc
Author: Explosion
Author-email: contact@explosion.ai
License: MIT
Classifier: Development Status :: 5 - Production/Stable
Classifier: Environment :: Console
Classifier: Intended Audience :: Developers
Classifier: Intended Audience :: Science/Research
Classifier: License :: OSI Approved :: MIT License
Classifier: Operating System :: POSIX :: Linux
Classifier: Operating System :: MacOS :: MacOS X
Classifier: Operating System :: Microsoft :: Windows
Classifier: Programming Language :: Cython
Classifier: Programming Language :: Python :: 3
Classifier: Programming Language :: Python :: 3.9
Classifier: Programming Language :: Python :: 3.10
Classifier: Programming Language :: Python :: 3.11
Classifier: Programming Language :: Python :: 3.12
Classifier: Topic :: Scientific/Engineering
Requires-Python: >=3.9
License-File: LICENSE
Requires-Dist: blis <1.1.0,>=1.0.0
Requires-Dist: murmurhash <1.1.0,>=1.0.2
Requires-Dist: cymem <2.1.0,>=2.0.2
Requires-Dist: preshed <3.1.0,>=3.0.2
Requires-Dist: wasabi <1.2.0,>=0.8.1
Requires-Dist: srsly <3.0.0,>=2.4.0
Requires-Dist: catalogue <2.1.0,>=2.0.4
Requires-Dist: confection <1.0.0,>=0.0.1
Requires-Dist: setuptools
Requires-Dist: numpy <3.0.0,>=2.0.0
Requires-Dist: pydantic !=1.8,!=1.8.1,<3.0.0,>=1.7.4
Requires-Dist: packaging >=20.0
Provides-Extra: cuda
Requires-Dist: cupy >=5.0.0b4 ; extra == 'cuda'
Provides-Extra: cuda-autodetect
Requires-Dist: cupy-wheel >=11.0.0 ; extra == 'cuda-autodetect'
Provides-Extra: cuda100
Requires-Dist: cupy-cuda100 >=5.0.0b4 ; extra == 'cuda100'
Provides-Extra: cuda101
Requires-Dist: cupy-cuda101 >=5.0.0b4 ; extra == 'cuda101'
Provides-Extra: cuda102
Requires-Dist: cupy-cuda102 >=5.0.0b4 ; extra == 'cuda102'
Provides-Extra: cuda110
Requires-Dist: cupy-cuda110 >=5.0.0b4 ; extra == 'cuda110'
Provides-Extra: cuda111
Requires-Dist: cupy-cuda111 >=5.0.0b4 ; extra == 'cuda111'
Provides-Extra: cuda112
Requires-Dist: cupy-cuda112 >=5.0.0b4 ; extra == 'cuda112'
Provides-Extra: cuda113
Requires-Dist: cupy-cuda113 >=5.0.0b4 ; extra == 'cuda113'
Provides-Extra: cuda114
Requires-Dist: cupy-cuda114 >=5.0.0b4 ; extra == 'cuda114'
Provides-Extra: cuda115
Requires-Dist: cupy-cuda115 >=5.0.0b4 ; extra == 'cuda115'
Provides-Extra: cuda116
Requires-Dist: cupy-cuda116 >=5.0.0b4 ; extra == 'cuda116'
Provides-Extra: cuda117
Requires-Dist: cupy-cuda117 >=5.0.0b4 ; extra == 'cuda117'
Provides-Extra: cuda11x
Requires-Dist: cupy-cuda11x >=11.0.0 ; extra == 'cuda11x'
Provides-Extra: cuda12x
Requires-Dist: cupy-cuda12x >=11.5.0 ; extra == 'cuda12x'
Provides-Extra: cuda80
Requires-Dist: cupy-cuda80 >=5.0.0b4 ; extra == 'cuda80'
Provides-Extra: cuda90
Requires-Dist: cupy-cuda90 >=5.0.0b4 ; extra == 'cuda90'
Provides-Extra: cuda91
Requires-Dist: cupy-cuda91 >=5.0.0b4 ; extra == 'cuda91'
Provides-Extra: cuda92
Requires-Dist: cupy-cuda92 >=5.0.0b4 ; extra == 'cuda92'
Provides-Extra: datasets
Requires-Dist: ml-datasets <0.3.0,>=0.2.0 ; extra == 'datasets'
Provides-Extra: mxnet
Requires-Dist: mxnet <1.6.0,>=1.5.1 ; extra == 'mxnet'
Provides-Extra: tensorflow
Requires-Dist: tensorflow <2.6.0,>=2.0.0 ; extra == 'tensorflow'
Provides-Extra: torch
Requires-Dist: torch >=1.6.0 ; extra == 'torch'
